cpc/__init__.py
cpc/app.py
cpc/common/__init__.py
cpc/common/config.py
cpc/common/const.py
cpc/database/__init__.py
cpc/database/dml/__init__.py
cpc/database/dml/asset.py
cpc/database/dml/favorite.py
cpc/database/dml/user.py
cpc/database/dml/init/__init__.py
cpc/database/dml/init/init.py
cpc/handlers/__init__.py
cpc/handlers/asset_controller.py
cpc/handlers/favorite_controller.py
cpc/handlers/kline_controller.py
cpc/handlers/price_controller.py
cpc/handlers/symbol_controller.py
cpc/handlers/user_controller.py
cpc/helpers/__init__.py
cpc/helpers/mexc.py
cpc/middlewares/db_connect.py
cpc/repositories/__init__.py
cpc/repositories/asset.py
cpc/repositories/favorite.py
cpc/repositories/user.py
cpc/services/asset.py
cpc/services/favorite.py
cpc/services/kline.py
cpc/services/price.py
cpc/services/symbol.py
cpc/services/user.py
cpc_py-1.0.1.dist-info/LICENSE
cpc_py-1.0.1.dist-info/METADATA
cpc_py-1.0.1.dist-info/WHEEL
cpc_py-1.0.1.dist-info/entry_points.txt
cpc_py-1.0.1.dist-info/top_level.txt
cpc_py-1.0.1.dist-info/RECORD
