Metadata-Version: 2.2
Name: cpc_py
Version: 1.0.1
Summary: A visually enhanced terminal application for real-time cryptocurrency price checks, K-line charts, and monitoring the total value of all virtual assets.
Author-email: Tom Yung <goodjobhot@gmail.com>
License: MIT License
Project-URL: Homepage, https://github.com/goodjobhot401/cpc_py
Project-URL: Issues, https://github.com/goodjobhot401/cpc_py/issues
Project-URL: Documentation, https://github.com/goodjobhot401/cpc_py/blob/main/Readme.md
Keywords: python,crypto,portfolio,terminal
Classifier: Intended Audience :: Developers
Classifier: Programming Language :: Python :: 3.13
Requires-Python: >=3.9
License-File: LICENSE
Requires-Dist: requests>=2.0
Requires-Dist: plotext>=5.3.2
Requires-Dist: rich>=13.9.4
